tagcounter/__init__.py
tagcounter/__main__.py
tagcounter/console.py
tagcounter/data.pickle
tagcounter/domains.yaml
tagcounter/gui.py
tagcounter/htmlParser.py
tagcounter/htmlReader.py
tagcounter/parser.db
tagcounter/tagService.py
tagcounter/urlParser.py
tagcounter/yamlService.py
tagcounter/DB/__init__.py
tagcounter/DB/domainRepo.py
tagcounter/DB/pageRepo.py
tagcounter/DB/models/__init__.py
tagcounter/DB/models/domain.py
tagcounter/DB/models/page.py
htmltg-1.5.12.dist-info/METADATA
htmltg-1.5.12.dist-info/WHEEL
htmltg-1.5.12.dist-info/entry_points.txt
htmltg-1.5.12.dist-info/top_level.txt
htmltg-1.5.12.dist-info/RECORD
