Metadata-Version: 2.1
Name: htmltg
Version: 1.5.12
Summary: app for counting tag of site page
Home-page: https://github.com/alenavysotskaya4324/tagcounter
Author: Elena Vysotskaya
Author-email: UNKNOWN
License: UNKNOWN
Platform: UNKNOWN
